introduction/acumulador_controlado.v
module acumulador_controlado (
    input wire clk, rst, en,
    input wire [1:0] sel,
    input wire [3:0] in,

    output reg [3:0] acc,  // Valor actual del acumulador
    output reg [3:0] next // Siguiente valor del acumulador
);
    always @(*) begin
        // Valor por defecto para evitar latches
        next = acc;

        case (sel)
            2'b00: next = acc + in; // Suma
            2'b01: next = acc - in; // Resta
            2'b10: next = acc ^ in; // XOR
            2'b11: next = acc;      // Mantener
        endcase
    end

    always @(posedge clk) begin
        if (rst)
            acc <= 4'b0000;  // Reinicia el acumulador a 0
        else if (en)
            acc <= next;
    end
endmodule

introduction/acumulador_controlado_tb.v
`timescale 1ns/1ps

module acumulador_controlado_tb;
    reg        clk, rst, en;
    reg  [1:0] sel;
    reg  [3:0] in;
    wire [3:0] acc, next;

    acumulador_controlado dut (
        .clk(clk),
        .rst(rst),
        .en(en),
        .sel(sel),
        .in(in),
        .acc(acc),
        .next(next)
    );

    // Clock de 10 ns de período
    initial begin
        clk = 0;
        forever #5 clk = ~clk;
    end

    initial begin
        $dumpfile("acumulador_controlado.vcd");
        $dumpvars(0, acumulador_controlado_tb);

        // Reset
        rst=1; en=0; sel=2'b00; in=4'd0; #12;
        rst=0;

        // Suma: 0 -> 3 -> 6
        en=1; sel=2'b00; in=4'd3; #10;
                               #10;

        // Resta: 6 - 2 = 4
        sel=2'b01; in=4'd2;     #10;

        // XOR: 4 ^ 15 = 11
        sel=2'b10; in=4'd15;    #10;

        // Mantener: acc sigue en 11
        sel=2'b11; in=4'd5;     #10;

        // en=0: no cambia
        en=0; sel=2'b00; in=4'd1; #10;

        $finish;
    end
endmodule

introduction/acumulador_controlado.vcd
$date
	Thu Aug 28 18:54:48 2025
$end
$version
	Icarus Verilog
$end
$timescale
	1ps
$end
$scope module acumulador_controlado_tb $end
$var wire 4 ! next [3:0] $end
$var wire 4 " acc [3:0] $end
$var reg 1 # clk $end
$var reg 1 $ en $end
$var reg 4 % in [3:0] $end
$var reg 1 & rst $end
$var reg 2 ' sel [1:0] $end
$scope module dut $end
$var wire 1 # clk $end
$var wire 1 $ en $end
$var wire 4 ( in [3:0] $end
$var wire 1 & rst $end
$var wire 2 ) sel [1:0] $end
$var reg 4 * acc [3:0] $end
$var reg 4 + next [3:0] $end
$upscope $end
$upscope $end
$enddefinitions $end
$comment Show the parameter values. $end
$dumpall
$end
#0
$dumpvars
bx +
bx *
b0 )
b0 (
b0 '
1&
b0 %
0$
0#
bx "
bx !
$end
#5000
b0 !
b0 +
b0 "
b0 *
1#
#10000
0#
#12000
b11 !
b11 +
b11 %
b11 (
1$
0&
#15000
b110 !
b110 +
b11 "
b11 *
1#
#20000
0#
#25000
b1001 !
b1001 +
b110 "
b110 *
1#
#30000
0#
#32000
b100 !
b100 +
b10 %
b10 (
b1 '
b1 )
#35000
b10 !
b10 +
b100 "
b100 *
1#
#40000
0#
#42000
b1011 !
b1011 +
b1111 %
b1111 (
b10 '
b10 )
#45000
b100 !
b100 +
b1011 "
b1011 *
1#
#50000
0#
#52000
b1011 !
b1011 +
b101 %
b101 (
b11 '
b11 )
#55000
1#
#60000
0#
#62000
b1100 !
b1100 +
b1 %
b1 (
b0 '
b0 )
0$
