introduction/cmp4.v
module cmp4 (
    input wire [3:0] a, b,
    output reg lt, gt, eq
);
    always @(*) begin
        // Valor por defectos para evitar latches
        lt = 1'b0;
        gt = 1'b0;
        eq = 1'b0;

        if (a < b) begin
            lt = 1'b1;
        end else if (a > b) begin
            gt = 1'b1;
        end else begin
            eq = 1'b1;
        end
    end
endmodule

introduction/cmp4_tb.v
`timescale 1ns/1ps

module cmp4_tb;
    reg  [3:0] a, b;
    wire lt, eq, gt;

    cmp4 dut (.a(a), .b(b), .lt(lt), .eq(eq), .gt(gt));

    initial begin
        $dumpfile("cmp4.vcd");
        $dumpvars(0, cmp4_tb);

        // Casos de prueba básicos
        a = 4'd0;  b = 4'd0;  #10;   // eq=1
        a = 4'd3;  b = 4'd7;  #10;   // lt=1
        a = 4'd8;  b = 4'd2;  #10;   // gt=1
        a = 4'd15; b = 4'd15; #10;   // eq=1
        a = 4'd9;  b = 4'd10; #10;   // lt=1
        a = 4'd10; b = 4'd9;  #10;   // gt=1

        // Barrido rápido
        a = 0; b = 0;
        repeat (8) begin
            #5 a = a + 1;
            #5 b = b + 2;
        end

        #10 $finish;
    end
endmodule

introduction/cmp4.vcd
$date
	Thu Aug 28 17:36:07 2025
$end
$version
	Icarus Verilog
$end
$timescale
	1ps
$end
$scope module cmp4_tb $end
$var wire 1 ! lt $end
$var wire 1 " gt $end
$var wire 1 # eq $end
$var reg 4 $ a [3:0] $end
$var reg 4 % b [3:0] $end
$scope module dut $end
$var wire 4 & a [3:0] $end
$var wire 4 ' b [3:0] $end
$var reg 1 # eq $end
$var reg 1 " gt $end
$var reg 1 ! lt $end
$upscope $end
$upscope $end
$enddefinitions $end
$comment Show the parameter values. $end
$dumpall
$end
#0
$dumpvars
b0 '
b0 &
b0 %
b0 $
1#
0"
0!
$end
#10000
1!
0#
b111 %
b111 '
b11 $
b11 &
#20000
1"
0!
b10 %
b10 '
b1000 $
b1000 &
#30000
1#
0"
b1111 %
b1111 '
b1111 $
b1111 &
#40000
1!
0#
b1010 %
b1010 '
b1001 $
b1001 &
#50000
1"
0!
b1001 %
b1001 '
b1010 $
b1010 &
#60000
1#
0"
b0 %
b0 '
b0 $
b0 &
#65000
1"
0#
b1 $
b1 &
#70000
1!
0"
b10 %
b10 '
#75000
1#
0!
b10 $
b10 &
#80000
1!
0#
b100 %
b100 '
#85000
1!
b11 $
b11 &
#90000
1!
b110 %
b110 '
#95000
1!
b100 $
b100 &
#100000
1!
b1000 %
b1000 '
#105000
1!
b101 $
b101 &
#110000
1!
b1010 %
b1010 '
#115000
1!
b110 $
b110 &
#120000
1!
b1100 %
b1100 '
#125000
1!
b111 $
b111 &
#130000
1!
b1110 %
b1110 '
#135000
1!
b1000 $
b1000 &
#140000
1"
0!
b0 %
b0 '
