introduction/shift_reg.v
module shift_reg (
    input wire clk,
    input wire rst,
    input wire din,
    output reg [3:0] q
);
    always @(posedge clk) begin
        if (rst)
            q <= 4'b0000;
        else
            q <= {q[2:0], din}; // Desplaza a la izquierda y agrega din en el LSB
    end
endmodule

introduction/shift_reg_tb.v
`timescale 1ns/1ps

module shift_reg_tb;
    reg clk, rst, din;
    wire [3:0] q;

    shift_reg dut (.clk(clk), .rst(rst), .din(din), .q(q));

    // Generador de clock
    initial begin
        clk = 0;
        forever #5 clk = ~clk; // periodo = 10 ns
    end

    initial begin
        $dumpfile("shift_reg.vcd");
        $dumpvars(0, shift_reg_tb);

        // Reset
        rst = 1; din = 0; #12;
        rst = 0;

        // Cargamos bits en serie
        din = 1; #10;
        din = 0; #10;
        din = 1; #10;
        din = 1; #10;
        din = 0; #10;

        #20 $finish;
    end
endmodule

introduction/shift_reg.vcd
$date
	Thu Aug 28 17:53:21 2025
$end
$version
	Icarus Verilog
$end
$timescale
	1ps
$end
$scope module shift_reg_tb $end
$var wire 4 ! q [3:0] $end
$var reg 1 " clk $end
$var reg 1 # din $end
$var reg 1 $ rst $end
$scope module dut $end
$var wire 1 " clk $end
$var wire 1 # din $end
$var wire 1 $ rst $end
$var reg 4 % q [3:0] $end
$upscope $end
$upscope $end
$enddefinitions $end
$comment Show the parameter values. $end
$dumpall
$end
#0
$dumpvars
bx %
1$
0#
0"
bx !
$end
#5000
b0 !
b0 %
1"
#10000
0"
#12000
1#
0$
#15000
b1 !
b1 %
1"
#20000
0"
#22000
0#
#25000
b10 !
b10 %
1"
#30000
0"
#32000
1#
#35000
b101 !
b101 %
1"
#40000
0"
#45000
b1011 !
b1011 %
1"
#50000
0"
#52000
0#
#55000
b110 !
b110 %
1"
#60000
0"
#65000
b1100 !
b1100 %
1"
#70000
0"
#75000
b1000 !
b1000 %
1"
